bilimusic/__init__.py
bilimusic/cli.py
bilimusic/mp3.py
bilimusic/urlconvert.py
bilimusic/utils.py
bilimusic/Video.py
bilimusic-1.0.2.dist-info/entry_points.txt
bilimusic-1.0.2.dist-info/METADATA
bilimusic-1.0.2.dist-info/WHEEL
bilimusic-1.0.2.dist-info/RECORD
