Metadata-Version: 2.1
Name: bilimusic
Version: 1.0.2
Summary: BiliMusic helps you to download mp3 music file from bilibili video. Compared to a lot of same type applications and scripts, BiliMusic can do more, it can set metadata on mp3 file automatically.
Author: aoout
Author-email: wuz66280@gmail.com
Requires-Python: >=3.7.0,<3.11
Classifier: Programming Language :: Python :: 3
Classifier: Programming Language :: Python :: 3.7
Classifier: Programming Language :: Python :: 3.8
Classifier: Programming Language :: Python :: 3.9
Classifier: Programming Language :: Python :: 3.10
Requires-Dist: eyed3 (>=0.9.6,<0.10.0)
Requires-Dist: fire (>=0.5.0,<0.6.0)
Requires-Dist: moviepy (>=1.0.3,<2.0.0)
Requires-Dist: pillow (>=9.2.0,<10.0.0)
Requires-Dist: pydub (>=0.25.1,<0.26.0)
Requires-Dist: requests (>=2.28.1,<3.0.0)
